djinn/__init__.py
djinn/loop.py
djinn/main.py
djinn/constant/__init__.py
djinn/constant/message.py
djinn/tools/__init__.py
djinn/tools/base.py
djinn/tools/bash.py
djinn/tools/collection.py
djinn/tools/edit.py
djinn/tools/run.py
djinn/utils/__init__.py
djinn/utils/console.py
djinn_agent-0.1.0.dist-info/LICENSE
djinn_agent-0.1.0.dist-info/METADATA
djinn_agent-0.1.0.dist-info/WHEEL
djinn_agent-0.1.0.dist-info/entry_points.txt
djinn_agent-0.1.0.dist-info/top_level.txt
djinn_agent-0.1.0.dist-info/RECORD
